pytuflow/TUFLOW.py
pytuflow/TUFLOW_results.py
pytuflow/TUFLOW_results2013.py
pytuflow/__init__.py
pytuflow/compatibility_routines.py
pytuflow/helper.py
pytuflow/logging_.py
pytuflow/pathlib_.py
pytuflow/tuflow_results_gpkg.py
pytuflow-0.0.17.dist-info/LICENSE.txt
pytuflow-0.0.17.dist-info/METADATA
pytuflow-0.0.17.dist-info/WHEEL
pytuflow-0.0.17.dist-info/top_level.txt
pytuflow-0.0.17.dist-info/RECORD
