Metadata-Version: 2.1
Name: pytuflow
Version: 0.0.17
Summary: Package for scripting TUFLOW time series results.
Home-page: https://github.com/TUFLOW-Support/PyTuflow
Author: tuflowsupport
Author-email: support@tuflow.com
Classifier: Programming Language :: Python :: 2.7
Classifier: Programming Language :: Python :: 3
Classifier: License :: OSI Approved :: GNU General Public License v3 (GPLv3)
Classifier: Operating System :: OS Independent
License-File: LICENSE.txt
Requires-Dist: numpy
Requires-Dist: netCDF4
Requires-Dist: python-dateutil
